turta_iothat/Turta_APDS9960.py
turta_iothat/Turta_BME280.py
turta_iothat/Turta_BME680.py
turta_iothat/Turta_IOPort.py
turta_iothat/Turta_MMA8491Q.py
turta_iothat/Turta_RelayController.py
turta_iothat/Turta_VEML6075.py
turta_iothat/__init__.py
turta_iothat-1.1.1.dist-info/LICENCE
turta_iothat-1.1.1.dist-info/METADATA
turta_iothat-1.1.1.dist-info/WHEEL
turta_iothat-1.1.1.dist-info/top_level.txt
turta_iothat-1.1.1.dist-info/RECORD
