Metadata-Version: 2.1
Name: turta-iothat
Version: 1.1.1
Summary: Python Libraries for Turta IoT HAT
Home-page: https://www.turta.io/iot-hat
Author: Turta LLC
Author-email: support@turta.io
License: UNKNOWN
Project-URL: Documentation, https://docs.turta.io/raspberry-pi-hats/iot-hat
Project-URL: Community, https://community.turta.io
Project-URL: GitHub Repository, https://github.com/Turta-io/IoTHAT
Platform: UNKNOWN
Classifier: Development Status :: 5 - Production/Stable
Classifier: Intended Audience :: Developers
Classifier: Programming Language :: Python
Classifier: License :: OSI Approved :: MIT License
Classifier: Operating System :: Unix
Classifier: Topic :: System :: Hardware
